{
  "id": "lei-n-o-10-99-de-7-de-julho-lei-de-florestas-e-fauna-bravia",
  "type": "statute",
  "title": "Lei n.o 10/99 de 7 de Julho - Lei de Florestas e Fauna Bravia",
  "title_en": "Lei n.o 10/99 de 7 de Julho - Lei de Florestas e Fauna Bravia",
  "short_name": "Lei n.o 10/99 de 7 de Julho - Lei de ...",
  "status": "in_force",
  "issued_date": "",
  "in_force_date": "",
  "url": "https://www.fao.org/faolex/country-profiles/general-profile/en/?iso3=MOZ",
  "provisions": [],
  "definitions": []
}